lazymodels/__init__.py
lazymodels/core.py
lazymodels/functional_only.py
lazymodels/wrappers.py
lazymodels-0.1.6.dist-info/METADATA
lazymodels-0.1.6.dist-info/WHEEL
lazymodels-0.1.6.dist-info/top_level.txt
lazymodels-0.1.6.dist-info/RECORD
