Metadata-Version: 2.4
Name: lazymodels
Version: 0.1.6
Summary: Smart lazy loader for Transformers with memory-based unloading (CPU/GPU aware)
Author: Nikita
Requires-Python: >=3.8
Requires-Dist: transformers
Requires-Dist: torch
Requires-Dist: psutil
Dynamic: author
Dynamic: description
Dynamic: description-content-type
Dynamic: requires-dist
Dynamic: requires-python
Dynamic: summary
